adpeek/__init__.py
adpeek/cli.py
adpeek_cli-0.1.2.dist-info/METADATA
adpeek_cli-0.1.2.dist-info/WHEEL
adpeek_cli-0.1.2.dist-info/entry_points.txt
adpeek_cli-0.1.2.dist-info/top_level.txt
adpeek_cli-0.1.2.dist-info/RECORD
