Metadata-Version: 2.4
Name: adpeek-cli
Version: 0.1.2
Summary: A lightweight Active Directory enumeration and ACL helper over LDAP.
Author: 0xUnd3adBeef
Project-URL: Homepage, https://github.com/0xUnd3adBeef/AdPeek
Project-URL: Repository, https://github.com/0xUnd3adBeef/AdPeek
Requires-Python: >=3.8
Requires-Dist: ldap3
